demo/__init__.py
demo/create_and_sync.py
demo/daphne.py
demo/desire.py
demo/fixtures.py
demo/main.py
demo/util.py
demo/celery/__init__.py
demo/celery/app.py
demo/celery/tasks.py
sync/__init__.py
sync/datasource.py
sync/mapping.py
sync/mixins.py
sync/operations.py
sync/syncer.py
sync/backends/__init__.py
sync/backends/inmemory.py
sync/backends/redislinkprovider.py
sync/backends/sqlalchemy.py
synchronizer_framework-0.0.22.dist-info/LICENSE
synchronizer_framework-0.0.22.dist-info/METADATA
synchronizer_framework-0.0.22.dist-info/WHEEL
synchronizer_framework-0.0.22.dist-info/top_level.txt
synchronizer_framework-0.0.22.dist-info/RECORD
