Metadata-Version: 2.1
Name: synchronizer-framework
Version: 0.0.22
Summary: Bi-directional synchronization of CRUD data sources
Home-page: https://gitlab.com/sebastianspies9/synchronizer-framework
Author: Sebastian Spies
Author-email: s+gitlab@sloc.de
License: UNKNOWN
Platform: UNKNOWN
Classifier: Programming Language :: Python :: 3
Classifier: License :: OSI Approved :: MIT License
Classifier: Operating System :: OS Independent
Requires-Python: >=3.8
License-File: LICENSE
